.clang-format
.flake8
.gitignore
.gitmodules
CHANGELOG.md
CODEOWNERS
CODE_OF_CONDUCT
Dockerfile
Dockerfile-cuda
Dockerfile-embedded
LICENSE
MANIFEST.in
Makefile
README.md
__init__.py
description.txt
packages.txt
setup.py
./src/opendr/__init__.py
./src/opendr/_setup.py
./src/opendr/_version.py
./src/opendr/control/__init__.py
./src/opendr/engine/__init__.py
./src/opendr/engine/constants.py
./src/opendr/engine/data.py
./src/opendr/engine/datasets.py
./src/opendr/engine/example_learner.py
./src/opendr/engine/learners.py
./src/opendr/engine/target.py
./src/opendr/perception/__init__.py
./src/opendr/perception/object_tracking_3d/__init__.py
./src/opendr/perception/object_tracking_3d/ab3dmot/.gitignore
./src/opendr/perception/object_tracking_3d/ab3dmot/README.md
./src/opendr/perception/object_tracking_3d/ab3dmot/__init__.py
./src/opendr/perception/object_tracking_3d/ab3dmot/dependencies.ini
./src/opendr/perception/object_tracking_3d/ab3dmot/logger.py
./src/opendr/perception/object_tracking_3d/ab3dmot/object_tracking_3d_ab3dmot_learner.py
./src/opendr/perception/object_tracking_3d/ab3dmot/algorithm/__init__.py
./src/opendr/perception/object_tracking_3d/ab3dmot/algorithm/ab3dmot.py
./src/opendr/perception/object_tracking_3d/ab3dmot/algorithm/core.py
./src/opendr/perception/object_tracking_3d/ab3dmot/algorithm/evaluate.py
./src/opendr/perception/object_tracking_3d/ab3dmot/algorithm/kalman_tracker_3d.py
./src/opendr/perception/object_tracking_3d/datasets/__init__.py
./src/opendr/perception/object_tracking_3d/datasets/kitti_siamese_tracking.py
./src/opendr/perception/object_tracking_3d/datasets/kitti_tracking.py
./src/opendr/perception/object_tracking_3d/single_object_tracking/vpit/.gitignore
./src/opendr/perception/object_tracking_3d/single_object_tracking/vpit/README.md
./src/opendr/perception/object_tracking_3d/single_object_tracking/vpit/dependencies.ini
./src/opendr/perception/object_tracking_3d/single_object_tracking/vpit/second_detector/configs/car.config
./src/opendr_toolkit_object_tracking_3d.egg-info/PKG-INFO
./src/opendr_toolkit_object_tracking_3d.egg-info/SOURCES.txt
./src/opendr_toolkit_object_tracking_3d.egg-info/dependency_links.txt
./src/opendr_toolkit_object_tracking_3d.egg-info/requires.txt
./src/opendr_toolkit_object_tracking_3d.egg-info/top_level.txt
